FibonacciHeap/FibonacciHeap.py
FibonacciHeap/__init__.py
FibonacciHeap-0.0.2.dist-info/LICENSE
FibonacciHeap-0.0.2.dist-info/METADATA
FibonacciHeap-0.0.2.dist-info/WHEEL
FibonacciHeap-0.0.2.dist-info/top_level.txt
FibonacciHeap-0.0.2.dist-info/RECORD
