Metadata-Version: 2.1
Name: FibonacciHeap
Version: 0.0.2
Summary: A Fibonacci Heap implementation
Author-email: Aditya <ashokadi@msu.edu>
Project-URL: Homepage, https://github.com/Ashok-Aditya/FibonacciHeap
Project-URL: Issues, https://github.com/Ashok-Aditya/FibonacciHeap/issues
Classifier: Programming Language :: Python :: 3
Classifier: License :: OSI Approved :: MIT License
Classifier: Operating System :: OS Independent
Requires-Python: >=3.8
License-File: LICENSE
